sota_extractor/__init__.py
sota_extractor/__main__.py
sota_extractor/consts.py
sota_extractor/errors.py
sota_extractor/import_nlp_progress_datasets.py
sota_extractor/serialization.py
sota_extractor/commands/__init__.py
sota_extractor/commands/cli.py
sota_extractor/commands/evaluate.py
sota_extractor/commands/scrapers.py
sota_extractor/scrapers/__init__.py
sota_extractor/scrapers/chexpert.py
sota_extractor/scrapers/cityscapes.py
sota_extractor/scrapers/cmrc.py
sota_extractor/scrapers/coqa.py
sota_extractor/scrapers/eff.py
sota_extractor/scrapers/hotpotqa.py
sota_extractor/scrapers/ogb.py
sota_extractor/scrapers/record.py
sota_extractor/scrapers/reddit.py
sota_extractor/scrapers/smcalflow.py
sota_extractor/scrapers/snli.py
sota_extractor/scrapers/squad.py
sota_extractor/scrapers/utils.py
sota_extractor/scrapers/xtreme.py
sota_extractor/scrapers/nlp_progress/__init__.py
sota_extractor/scrapers/nlp_progress/__main__.py
sota_extractor/scrapers/nlp_progress/fixer.py
sota_extractor/scrapers/nlp_progress/main.py
sota_extractor/scrapers/nlp_progress/markdown.py
sota_extractor/scrapers/nlp_progress/parsers.py
sota_extractor/scrapers/nlp_progress/printer.py
sota_extractor/taskdb/__init__.py
sota_extractor/taskdb/v01/__init__.py
sota_extractor/taskdb/v01/models.py
sota_extractor/taskdb/v01/schemas.py
sota_extractor/taskdb/v01/taskdb.py
sota_extractor/tests/__init__.py
sota_extractor/tests/test_load_save.py
sota_extractor-0.0.29.dist-info/LICENSE
sota_extractor-0.0.29.dist-info/METADATA
sota_extractor-0.0.29.dist-info/WHEEL
sota_extractor-0.0.29.dist-info/entry_points.txt
sota_extractor-0.0.29.dist-info/top_level.txt
sota_extractor-0.0.29.dist-info/RECORD
