Metadata-Version: 2.1
Name: sota-extractor
Version: 0.0.29
Summary: Automatic SOTA (state-of-the-art) extraction.
Home-page: https://github.com/paperswithcode/sota-extractor
Author: Robert Stojnic
Author-email: robert@atlasml.io
Maintainer: Viktor Kerkez
Maintainer-email: viktor@atlasml.io
License: Apache-2.0
Keywords: sota table
Platform: Windows
Platform: POSIX
Platform: MacOS
Classifier: Intended Audience :: Developers
Classifier: Natural Language :: English
Classifier: Operating System :: POSIX
Classifier: Programming Language :: Python :: 3
Requires-Dist: beautifulsoup4 (~=4.9.0)
Requires-Dist: click (~=8.0.1)
Requires-Dist: jsonnet (~=0.17.0)
Requires-Dist: lxml (>=4.6.2)
Requires-Dist: markdown (~=3.3.4)
Requires-Dist: marshmallow (~=3.12.2)
Requires-Dist: nltk (~=3.4.5)
Requires-Dist: pandas
Requires-Dist: pytz (~=2021.1)
Requires-Dist: requests (~=2.23.0)
Requires-Dist: soupsieve (~=2.0)
